{
  "url": "http://127.0.0.1:4173/",
  "headingVisible": true,
  "generatedBannerCheckpoint": true,
  "segmentResearchCheckpoint": true,
  "todoConversionCheckpoint": true,
  "mindMapConversionCheckpoint": true,
  "momentCards": 5,
  "researchDrafts": 2,
  "sourceTraceVisible": true,
  "conversionActionsVisible": true,
  "businessConsoleErrors": [],
  "ignoredResourceErrors": [],
  "screenshotPath": "/Users/wwh/Documents/AI项目管理/shengji_mac/AI文档/版本归档/v0.9.0/v0.9.0-functional-review-value-discovery.png"
}